MANIFEST.in
setup.py
codenode/__init__.py
codenode/service.py
codenode.egg-info/PKG-INFO
codenode.egg-info/SOURCES.txt
codenode.egg-info/dependency_links.txt
codenode.egg-info/requires.txt
codenode.egg-info/top_level.txt
codenode/backend/__init__.py
codenode/backend/_devel_settings.py
codenode/backend/_settings.py
codenode/backend/core.py
codenode/backend/engine.py
codenode/backend/server.py
codenode/data/codenode.db
codenode/engine/__init__.py
codenode/engine/completer.py
codenode/engine/interpreter.py
codenode/engine/introspection.py
codenode/engine/outputtrap.py
codenode/engine/runtime.py
codenode/engine/server.py
codenode/engine/sage/__init__.py
codenode/engine/sage/interpreter.py
codenode/engine/sage/runtime.py
codenode/external/__init__.py
codenode/external/mmaplotlib/__init__.py
codenode/external/mmaplotlib/axes.py
codenode/external/mmaplotlib/codenode_plot.py
codenode/external/mmaplotlib/knoboo_plot.py
codenode/external/mmaplotlib/plot.py
codenode/frontend/__init__.py
codenode/frontend/_devel_settings.py
codenode/frontend/_settings.py
codenode/frontend/urls.py
codenode/frontend/async/__init__.py
codenode/frontend/async/backend.py
codenode/frontend/async/check.py
codenode/frontend/async/dbmanager.py
codenode/frontend/backend/__init__.py
codenode/frontend/backend/admin.py
codenode/frontend/backend/manager.py
codenode/frontend/backend/models.py
codenode/frontend/backend/rpc.py
codenode/frontend/backend/urls.py
codenode/frontend/backend/views.py
codenode/frontend/backend/fixtures/__init__.py
codenode/frontend/backend/fixtures/development.py
codenode/frontend/bookshelf/__init__.py
codenode/frontend/bookshelf/admin.py
codenode/frontend/bookshelf/models.py
codenode/frontend/bookshelf/tests.py
codenode/frontend/bookshelf/urls.py
codenode/frontend/bookshelf/views.py
codenode/frontend/notebook/__init__.py
codenode/frontend/notebook/admin.py
codenode/frontend/notebook/forms.py
codenode/frontend/notebook/models.py
codenode/frontend/notebook/revision.py
codenode/frontend/notebook/revision_utils.py
codenode/frontend/notebook/tests.py
codenode/frontend/notebook/urls.py
codenode/frontend/notebook/views.py
