Metadata-Version: 1.0
Name: codenode
Version: 0.02
Summary: Interactive Programming Notebook for the Web Browser
Home-page: http://codenode.org
Author: Alex Clemesha & Dorian Raymer
Author-email: codenode-devel@googlegroups.com
License: BSD
Download-URL: http://pypi.python.org/pypi/codenode
Platform: UNKNOWN
Classifier: Development Status :: 3 - Alpha
